gridslice/__init__.py
gridslice-1.0.0.dist-info/LICENSE
gridslice-1.0.0.dist-info/METADATA
gridslice-1.0.0.dist-info/WHEEL
gridslice-1.0.0.dist-info/entry_points.txt
gridslice-1.0.0.dist-info/top_level.txt
gridslice-1.0.0.dist-info/RECORD
